fastagi/__init__.py
fastagi/tools/__init__.py
fastagi/tools/base_tool.py
fastagi/types/__init__.py
fastagi/types/key_type.py
fastagi_tools-1.0.8.dist-info/LICENSE
fastagi_tools-1.0.8.dist-info/METADATA
fastagi_tools-1.0.8.dist-info/WHEEL
fastagi_tools-1.0.8.dist-info/top_level.txt
fastagi_tools-1.0.8.dist-info/RECORD
