Metadata-Version: 2.1
Name: fastagi_tools
Version: 1.0.8
Summary: fastagi-tools is a python library specifically designed for developers working with FastAGI. The library offers the BaseToolkit and BaseTool classes, requierd for development of custom tools and toolkits for FastAGI.
Author: fastagi
Author-email: info@khulnasoft.com
License-File: LICENSE
Requires-Dist: pydantic ==1.10.13
Requires-Dist: PyYAML ==6.0
